uqbar/__init__.py
uqbar/_version.py
uqbar/enums.py
uqbar/io.py
uqbar/iterables.py
uqbar/objects.py
uqbar/py.typed
uqbar/strings.py
uqbar/apis/__init__.py
uqbar/apis/builders.py
uqbar/apis/documenters.py
uqbar/apis/dummy.py
uqbar/apis/graphs.py
uqbar/apis/nodes.py
uqbar/apis/summarizers.py
uqbar/book/__init__.py
uqbar/book/extensions.py
uqbar/containers/__init__.py
uqbar/containers/dependency_graph.py
uqbar/containers/unique_tree.py
uqbar/ext/__init__.py
uqbar/ext/ipython.py
uqbar/graphs/__init__.py
uqbar/graphs/attrs.py
uqbar/graphs/core.py
uqbar/graphs/graphers.py
uqbar/graphs/html.py
uqbar/graphs/records.py
uqbar/sphinx/__init__.py
uqbar/sphinx/api.py
uqbar/sphinx/book.py
uqbar/sphinx/inheritance.py
uqbar/sphinx/style.py
uqbar/sphinx/uqbar.css
uqbar-0.9.6.dist-info/licenses/LICENSE
uqbar-0.9.6.dist-info/METADATA
uqbar-0.9.6.dist-info/WHEEL
uqbar-0.9.6.dist-info/top_level.txt
uqbar-0.9.6.dist-info/RECORD
